OptiDamTool/__init__.py
OptiDamTool/analysis.py
OptiDamTool/network.py
OptiDamTool/system_design.py
OptiDamTool/utility.py
OptiDamTool/visual.py
OptiDamTool/watem_sedem.py
optidamtool-0.5.0.dist-info/licenses/LICENSE
optidamtool-0.5.0.dist-info/METADATA
optidamtool-0.5.0.dist-info/WHEEL
optidamtool-0.5.0.dist-info/top_level.txt
optidamtool-0.5.0.dist-info/RECORD
