Metadata-Version: 2.4
Name: OptiDamTool
Version: 0.5.0
Summary: A Python package for analytics in dam management workflows.
Author-email: Debasish Pal <bestdebasish@gmail.com>
License-Expression: MIT
Project-URL: Homepage, https://github.com/debpal/OptiDamTool
Project-URL: Documentation, https://optidamtool.readthedocs.io/en/latest/
Keywords: Erosion,Sedimentation,Hydrologic modeling,Dam management,Optimization,Decision support
Classifier: Development Status :: 4 - Beta
Classifier: Programming Language :: Python :: 3.10
Classifier: Programming Language :: Python :: 3.11
Classifier: Programming Language :: Python :: 3.12
Classifier: Programming Language :: Python :: 3.13
Classifier: Operating System :: OS Independent
Classifier: Intended Audience :: Education
Classifier: Intended Audience :: Science/Research
Classifier: Topic :: Scientific/Engineering
Classifier: Topic :: Scientific/Engineering :: GIS
Classifier: Topic :: Scientific/Engineering :: Hydrology
Requires-Python: >=3.10
License-File: LICENSE
Requires-Dist: GeoAnalyze
Requires-Dist: beautifulsoup4
Requires-Dist: Platypus-opt
Dynamic: license-file
